faster_app/.env.example
faster_app/__init__.py
faster_app/app.py
faster_app/cli.py
faster_app/main.py
faster_app/apps/demo/commands.py
faster_app/apps/demo/models.py
faster_app/apps/demo/routes.py
faster_app/apps/demo/schemas.py
faster_app/apps/demo/tasks.py
faster_app/commands/__init__.py
faster_app/commands/base.py
faster_app/commands/discover.py
faster_app/commands/builtins/__init__.py
faster_app/commands/builtins/app.py
faster_app/commands/builtins/db.py
faster_app/commands/builtins/server.py
faster_app/config/settings.py
faster_app/middleware/discover.py
faster_app/middleware/builtins/middlewares.py
faster_app/models/__init__.py
faster_app/models/base.py
faster_app/models/discover.py
faster_app/routes/__init__.py
faster_app/routes/base.py
faster_app/routes/discover.py
faster_app/routes/builtins/__init__.py
faster_app/routes/builtins/defaults.py
faster_app/routes/builtins/swagger.py
faster_app/runtime/Dockerfile
faster_app/settings/__init__.py
faster_app/settings/config.py
faster_app/settings/discover.py
faster_app/settings/logging.py
faster_app/settings/builtins/settings.py
faster_app/settings/groups/__init__.py
faster_app/settings/groups/database.py
faster_app/settings/groups/jwt.py
faster_app/settings/groups/log.py
faster_app/settings/groups/server.py
faster_app/statics/swagger-ui-bundle.min.js
faster_app/statics/swagger-ui.min.css
faster_app/utils/__init__.py
faster_app/utils/crud.py
faster_app/utils/db.py
faster_app/utils/decorators.py
faster_app/utils/discover.py
faster_app/utils/response.py
faster_app-0.1.1.dist-info/licenses/LICENSE
faster_app-0.1.1.dist-info/METADATA
faster_app-0.1.1.dist-info/WHEEL
faster_app-0.1.1.dist-info/entry_points.txt
faster_app-0.1.1.dist-info/top_level.txt
faster_app-0.1.1.dist-info/RECORD
