Metadata-Version: 2.4
Name: faster_app
Version: 0.1.1
Summary: 一个轻量级的 Python Web 框架, 提供自动发现、模型基类、命令行工具等功能
Author-email: peizhenfei <peizhenfei@hotmail.com>
Maintainer-email: peizhenfei <peizhenfei@hotmail.com>
License-Expression: MIT
Project-URL: Homepage, https://github.com/mautops/faster_app
Project-URL: Documentation, https://github.com/mautops/faster_app#readme
Project-URL: Repository, https://github.com/mautops/faster_app.git
Project-URL: Bug Tracker, https://github.com/mautops/faster_app/issues
Keywords: web,framework,fastapi,tortoise,orm,cli
Requires-Python: >=3.12
License-File: LICENSE
Requires-Dist: aerich>=0.9.1
Requires-Dist: asyncpg>=0.30.0
Requires-Dist: fastapi>=0.116.1
Requires-Dist: fastapi-pagination>=0.14.1
Requires-Dist: fire>=0.7.1
Requires-Dist: pydantic>=2.11.7
Requires-Dist: pydantic-settings>=2.10.1
Requires-Dist: rich>=14.1.0
Requires-Dist: tortoise-orm[asyncpg]>=0.25.1
Requires-Dist: uvicorn>=0.35.0
Dynamic: license-file
